helloworld.py
helloworld_marndr-0.0.1.dist-info/LICENSE.txt
helloworld_marndr-0.0.1.dist-info/METADATA
helloworld_marndr-0.0.1.dist-info/WHEEL
helloworld_marndr-0.0.1.dist-info/top_level.txt
helloworld_marndr-0.0.1.dist-info/RECORD
