Metadata-Version: 2.1
Name: helloworld-marndr
Version: 0.0.1
Summary: say hello
Home-page: https://github.com/marndr/helloworld.git
Author: Maryam NAderi
Author-email: maryam.naderi@idiap.ch
Classifier: Programming Language :: Python :: 3
License-File: LICENSE.txt
